ensembl_tui/__init__.py
ensembl_tui/_align.py
ensembl_tui/_annotation.py
ensembl_tui/_cli_option.py
ensembl_tui/_config.py
ensembl_tui/_download.py
ensembl_tui/_emf.py
ensembl_tui/_ftp_download.py
ensembl_tui/_genome.py
ensembl_tui/_homology.py
ensembl_tui/_ingest_align.py
ensembl_tui/_ingest_annotation.py
ensembl_tui/_ingest_homology.py
ensembl_tui/_install.py
ensembl_tui/_maf.py
ensembl_tui/_mysql_core_attr.py
ensembl_tui/_name.py
ensembl_tui/_site_map.py
ensembl_tui/_species.py
ensembl_tui/_storage_mixin.py
ensembl_tui/_util.py
ensembl_tui/cli.py
ensembl_tui/data/__init__.py
ensembl_tui/data/sample.cfg
ensembl_tui/data/species.tsv
ensembl_tui-0.7.5.dist-info/entry_points.txt
ensembl_tui-0.7.5.dist-info/licenses/LICENSE
ensembl_tui-0.7.5.dist-info/WHEEL
ensembl_tui-0.7.5.dist-info/METADATA
ensembl_tui-0.7.5.dist-info/RECORD
