Metadata-Version: 2.4
Name: ensembl_tui
Version: 0.7.5
Summary: Ensembl terminal user interface tools
Keywords: biology,genomics,evolution,bioinformatics
Author-email: Gavin Huttley <Gavin.Huttley@anu.edu.au>, Arne Becker <arne@ebi.ac.uk>, Stefano Giorgetti <sgiorgetti@ebi.ac.uk>
Maintainer-email: Gavin Huttley <Gavin.Huttley@anu.edu.au>, Arne Becker <arne@ebi.ac.uk>, Stefano Giorgetti <sgiorgetti@ebi.ac.uk>
Requires-Python: >=3.11,<3.15
Classifier: Development Status :: 2 - Pre-Alpha
Classifier: Intended Audience :: Science/Research
Classifier: License :: OSI Approved :: BSD License
Classifier: Topic :: Scientific/Engineering :: Bio-Informatics
Classifier: Topic :: Software Development :: Libraries :: Python Modules
Classifier: Operating System :: OS Independent
Classifier: Programming Language :: Python :: 3.11
Classifier: Programming Language :: Python :: 3.12
Classifier: Programming Language :: Python :: 3.13
Classifier: Programming Language :: Python :: 3.14
License-File: LICENSE
Requires-Dist: click
Requires-Dist: cogent3==2026.1.12a1
Requires-Dist: cogent3-h5seqs==0.7.3
Requires-Dist: duckdb
Requires-Dist: numba
Requires-Dist: numpy
Requires-Dist: polars
Requires-Dist: pyarrow
Requires-Dist: rich
Requires-Dist: scitrack
Requires-Dist: typing_extensions
Requires-Dist: trogon
Requires-Dist: unsync
Requires-Dist: wakepy>0.7; os_name == 'darwin'
Requires-Dist: cogapp ; extra == "dev"
Requires-Dist: flit ; extra == "dev"
Requires-Dist: numpydoc ; extra == "dev"
Requires-Dist: psutil ; extra == "dev"
Requires-Dist: scriv ; extra == "dev"
Requires-Dist: ensembl_tui[doc] ; extra == "dev"
Requires-Dist: ensembl_tui[test] ; extra == "dev"
Requires-Dist: mkdocs>=1.6.1 ; extra == "doc"
Requires-Dist: markdown-exec[ansi]>=1.10.0 ; extra == "doc"
Requires-Dist: mkdocs-jupyter>=0.25.1 ; extra == "doc"
Requires-Dist: markdown>=3.7 ; extra == "doc"
Requires-Dist: mdformat ; extra == "doc"
Requires-Dist: mdformat-mkdocs ; extra == "doc"
Requires-Dist: mdformat-black ; extra == "doc"
Requires-Dist: pytest ; extra == "test"
Requires-Dist: pytest-cov ; extra == "test"
Requires-Dist: pytest-timeout ; extra == "test"
Requires-Dist: pytest-xdist ; extra == "test"
Requires-Dist: ruff==0.14.11 ; extra == "test"
Requires-Dist: nox ; extra == "test"
Project-URL: Bug Tracker, https://github.com/cogent3/ensembl_tui/issues
Project-URL: Documentation, https://ensembl-tui.readthedocs.io/
Project-URL: Source Code, https://github.com/cogent3/ensembl_tui
Provides-Extra: dev
Provides-Extra: doc
Provides-Extra: test
